{
  "intersection_osm_node_id": 2776431145,
  "phases": [
    {
      "protected_turns": [
        {
          "from": {
            "osm_way_id": 98534336,
            "osm_node1": 29972814,
            "osm_node2": 2776431145,
            "is_forwards": true
          },
          "to": {
            "osm_way_id": 682188082,
            "osm_node1": 2776431145,
            "osm_node2": 6388490087,
            "is_forwards": false
          },
          "intersection_osm_node_id": 2776431145,
          "is_crosswalk": true
        },
        {
          "from": {
            "osm_way_id": 272711583,
            "osm_node1": 59712558,
            "osm_node2": 2776431145,
            "is_forwards": true
          },
          "to": {
            "osm_way_id": 682188082,
            "osm_node1": 2776431145,
            "osm_node2": 6388490087,
            "is_forwards": true
          },
          "intersection_osm_node_id": 2776431145,
          "is_crosswalk": false
        },
        {
          "from": {
            "osm_way_id": 682188082,
            "osm_node1": 2776431145,
            "osm_node2": 6388490087,
            "is_forwards": false
          },
          "to": {
            "osm_way_id": 98534336,
            "osm_node1": 29972814,
            "osm_node2": 2776431145,
            "is_forwards": true
          },
          "intersection_osm_node_id": 2776431145,
          "is_crosswalk": true
        },
        {
          "from": {
            "osm_way_id": 682188082,
            "osm_node1": 2776431145,
            "osm_node2": 6388490087,
            "is_forwards": false
          },
          "to": {
            "osm_way_id": 272711583,
            "osm_node1": 59712558,
            "osm_node2": 2776431145,
            "is_forwards": false
          },
          "intersection_osm_node_id": 2776431145,
          "is_crosswalk": false
        }
      ],
      "permitted_turns": [
        {
          "from": {
            "osm_way_id": 682188082,
            "osm_node1": 2776431145,
            "osm_node2": 6388490087,
            "is_forwards": false
          },
          "to": {
            "osm_way_id": 6406131,
            "osm_node1": 2776431145,
            "osm_node2": 53155793,
            "is_forwards": true
          },
          "intersection_osm_node_id": 2776431145,
          "is_crosswalk": false
        }
      ],
      "phase_type": {
        "Fixed": 30
      }
    },
    {
      "protected_turns": [
        {
          "from": {
            "osm_way_id": 98534336,
            "osm_node1": 29972814,
            "osm_node2": 2776431145,
            "is_forwards": true
          },
          "to": {
            "osm_way_id": 6406131,
            "osm_node1": 2776431145,
            "osm_node2": 53155793,
            "is_forwards": true
          },
          "intersection_osm_node_id": 2776431145,
          "is_crosswalk": false
        },
        {
          "from": {
            "osm_way_id": 272711583,
            "osm_node1": 59712558,
            "osm_node2": 2776431145,
            "is_forwards": false
          },
          "to": {
            "osm_way_id": 272711583,
            "osm_node1": 59712558,
            "osm_node2": 2776431145,
            "is_forwards": true
          },
          "intersection_osm_node_id": 2776431145,
          "is_crosswalk": true
        },
        {
          "from": {
            "osm_way_id": 272711583,
            "osm_node1": 59712558,
            "osm_node2": 2776431145,
            "is_forwards": true
          },
          "to": {
            "osm_way_id": 272711583,
            "osm_node1": 59712558,
            "osm_node2": 2776431145,
            "is_forwards": false
          },
          "intersection_osm_node_id": 2776431145,
          "is_crosswalk": true
        },
        {
          "from": {
            "osm_way_id": 682188082,
            "osm_node1": 2776431145,
            "osm_node2": 6388490087,
            "is_forwards": false
          },
          "to": {
            "osm_way_id": 682188082,
            "osm_node1": 2776431145,
            "osm_node2": 6388490087,
            "is_forwards": true
          },
          "intersection_osm_node_id": 2776431145,
          "is_crosswalk": true
        },
        {
          "from": {
            "osm_way_id": 682188082,
            "osm_node1": 2776431145,
            "osm_node2": 6388490087,
            "is_forwards": true
          },
          "to": {
            "osm_way_id": 682188082,
            "osm_node1": 2776431145,
            "osm_node2": 6388490087,
            "is_forwards": false
          },
          "intersection_osm_node_id": 2776431145,
          "is_crosswalk": true
        }
      ],
      "permitted_turns": [
        {
          "from": {
            "osm_way_id": 98534336,
            "osm_node1": 29972814,
            "osm_node2": 2776431145,
            "is_forwards": true
          },
          "to": {
            "osm_way_id": 272711583,
            "osm_node1": 59712558,
            "osm_node2": 2776431145,
            "is_forwards": false
          },
          "intersection_osm_node_id": 2776431145,
          "is_crosswalk": false
        },
        {
          "from": {
            "osm_way_id": 98534336,
            "osm_node1": 29972814,
            "osm_node2": 2776431145,
            "is_forwards": true
          },
          "to": {
            "osm_way_id": 682188082,
            "osm_node1": 2776431145,
            "osm_node2": 6388490087,
            "is_forwards": true
          },
          "intersection_osm_node_id": 2776431145,
          "is_crosswalk": false
        }
      ],
      "phase_type": {
        "Fixed": 15
      }
    }
  ],
  "offset_seconds": 0
}
